{
	"data": [
		{
			"name": "campaign 1",
			"type": 0,
			"promoDt": "2015-02-01 ~ 2015-04-01",
			"rewardDlDt": "2015-02-01",
			"rewardClmDt": "2015-02-01",
			"reward": "38",
			"state": 8
		},
		{
			"name": "campaign 2",
			"type": 1,
			"promoDt": "2015-02-01 ~ 2015-04-01",
			"rewardDlDt": "2015-02-01",
			"rewardClmDt": "2015-02-01",
			"reward": "0.26",
			"state": 8
		},
		{
			"name": "campaign 3",
			"type": 3,
			"promoDt": "2015-02-01 ~ 2015-04-01",
			"rewardDlDt": "2015-02-01",
			"rewardClmDt": "2015-02-01",
			"reward": "24",
			"state": 8
		},
		{
			"name": "campaign 4",
			"type": 2,
			"promoDt": "2015-02-01 ~ 2015-04-01",
			"rewardDlDt": "2015-02-01",
			"rewardClmDt": "2015-02-01",
			"reward": "15",
			"state": 8
		},
		{
			"name": "campaign 4",
			"type": 2,
			"promoDt": "2015-02-01 ~ 2015-04-01",
			"rewardDlDt": "2015-02-01",
			"rewardClmDt": "2015-02-01",
			"reward": "15",
			"state": 8
		},
		{
			"name": "campaign 4",
			"type": 2,
			"promoDt": "2015-02-01 ~ 2015-04-01",
			"rewardDlDt": "2015-02-01",
			"rewardClmDt": "2015-02-01",
			"reward": "15",
			"state": 8
		}
	],
	"status": true
}